DarkGram/D_DataBase.py
DarkGram/D_items.py
DarkGram/DarkGram.py
DarkGram/__init__.py
DarkGram-0.0.1.dist-info/METADATA
DarkGram-0.0.1.dist-info/WHEEL
DarkGram-0.0.1.dist-info/top_level.txt
DarkGram-0.0.1.dist-info/RECORD
