Metadata-Version: 2.1
Name: DarkGram
Version: 0.0.1
Summary: DarkGram
Home-page: UNKNOWN
Author: vsp210
Author-email: psv449@yandex.ru
License: UNKNOWN
Platform: UNKNOWN
Requires-Dist: requests>=2.32.3
